unify_tensors/__init__.py
unify_tensors/typing.py
unify_tensors/unify_tensors.py
unify_tensors-0.1.3.dist-info/licenses/LICENSE
unify_tensors-0.1.3.dist-info/METADATA
unify_tensors-0.1.3.dist-info/WHEEL
unify_tensors-0.1.3.dist-info/top_level.txt
unify_tensors-0.1.3.dist-info/RECORD
