Metadata-Version: 2.4
Name: unify-tensors
Version: 0.1.3
Summary: A utility to unify the device of multiple PyTorch tensors.
Author-email: Giacomo Guiduzzi <guiduzzi.giacomo@gmail.com>
Project-URL: Homepage, https://github.com/giacomoguiduzzi/unify-tensors
Project-URL: Repository, https://github.com/giacomoguiduzzi/unify-tensors
Project-URL: Issues, https://github.com/giacomoguiduzzi/unify-tensors/issues
Classifier: Programming Language :: Python :: 3
Classifier: License :: OSI Approved :: MIT License
Classifier: Operating System :: OS Independent
Classifier: Intended Audience :: Developers
Classifier: Intended Audience :: Science/Research
Classifier: Topic :: Scientific/Engineering :: Artificial Intelligence
Classifier: Topic :: Software Development :: Libraries
Classifier: Topic :: Software Development :: Libraries :: Python Modules
Requires-Python: >=3.8
License-File: LICENSE
Requires-Dist: torch
Dynamic: license-file
